strings_repository/__init__.py
strings_repository/__main__.py
strings_repository/cli.py
strings_repository/strings_repository.py
strings_repository-0.2.0.data/scripts/strings_repository
strings_repository-0.2.0.dist-info/LICENSE
strings_repository-0.2.0.dist-info/METADATA
strings_repository-0.2.0.dist-info/WHEEL
strings_repository-0.2.0.dist-info/top_level.txt
strings_repository-0.2.0.dist-info/RECORD
